benedict/__init__.py
benedict/exceptions.py
benedict/extras.py
benedict/metadata.py
benedict/py.typed
benedict/core/__init__.py
benedict/core/clean.py
benedict/core/clone.py
benedict/core/dump.py
benedict/core/filter.py
benedict/core/find.py
benedict/core/flatten.py
benedict/core/groupby.py
benedict/core/invert.py
benedict/core/items_sorted.py
benedict/core/keylists.py
benedict/core/keypaths.py
benedict/core/match.py
benedict/core/merge.py
benedict/core/move.py
benedict/core/nest.py
benedict/core/remove.py
benedict/core/rename.py
benedict/core/search.py
benedict/core/standardize.py
benedict/core/subset.py
benedict/core/swap.py
benedict/core/traverse.py
benedict/core/unflatten.py
benedict/core/unique.py
benedict/dicts/__init__.py
benedict/dicts/base/__init__.py
benedict/dicts/base/base_dict.py
benedict/dicts/io/__init__.py
benedict/dicts/io/io_dict.py
benedict/dicts/io/io_util.py
benedict/dicts/keyattr/__init__.py
benedict/dicts/keyattr/keyattr_dict.py
benedict/dicts/keylist/__init__.py
benedict/dicts/keylist/keylist_dict.py
benedict/dicts/keylist/keylist_util.py
benedict/dicts/keypath/__init__.py
benedict/dicts/keypath/keypath_dict.py
benedict/dicts/keypath/keypath_util.py
benedict/dicts/parse/__init__.py
benedict/dicts/parse/parse_dict.py
benedict/dicts/parse/parse_util.py
benedict/serializers/__init__.py
benedict/serializers/abstract.py
benedict/serializers/base64.py
benedict/serializers/cli.py
benedict/serializers/csv.py
benedict/serializers/html.py
benedict/serializers/ini.py
benedict/serializers/json.py
benedict/serializers/pickle.py
benedict/serializers/plist.py
benedict/serializers/query_string.py
benedict/serializers/toml.py
benedict/serializers/xls.py
benedict/serializers/xml.py
benedict/serializers/yaml.py
benedict/utils/__init__.py
benedict/utils/type_util.py
python_benedict-0.35.0.dist-info/licenses/LICENSE.txt
python_benedict-0.35.0.dist-info/METADATA
python_benedict-0.35.0.dist-info/WHEEL
python_benedict-0.35.0.dist-info/top_level.txt
python_benedict-0.35.0.dist-info/RECORD
