Metadata-Version: 2.4
Name: python-benedict
Version: 0.35.0
Summary: python-benedict is a dict subclass with keylist/keypath/keyattr support, normalized I/O operations (base64, csv, ini, json, pickle, plist, query-string, toml, xls, xml, yaml) and many utilities... for humans, obviously.
Author-email: Fabio Caccamo <fabio.caccamo@gmail.com>
Maintainer-email: Fabio Caccamo <fabio.caccamo@gmail.com>
License: MIT License
Project-URL: Homepage, https://github.com/fabiocaccamo/python-benedict
Project-URL: Download, https://github.com/fabiocaccamo/python-benedict/releases
Project-URL: Documentation, https://github.com/fabiocaccamo/python-benedict#readme
Project-URL: Issues, https://github.com/fabiocaccamo/python-benedict/issues
Project-URL: Funding, https://github.com/sponsors/fabiocaccamo/
Project-URL: Twitter, https://twitter.com/fabiocaccamo
Keywords: python,dictionary,dictionaries,dict,benedict,subclass,extended,keylist,keypath,utility,io,data,file,url,read,write,parse,configparser,config,cfg,pickle,plist,base64,csv,html,ini,json,query-string,toml,xml,yaml,clean,clone,deepclone,deepupdate,dump,filter,flatten,groupby,invert,merge,move,nest,remove,rename,search,standardize,subset,swap,traverse,unflatten,unique
Classifier: Development Status :: 5 - Production/Stable
Classifier: Environment :: MacOS X
Classifier: Environment :: Other Environment
Classifier: Environment :: Web Environment
Classifier: Environment :: Win32 (MS Windows)
Classifier: Intended Audience :: Developers
Classifier: Intended Audience :: Education
Classifier: Intended Audience :: Information Technology
Classifier: Intended Audience :: Science/Research
Classifier: Intended Audience :: System Administrators
Classifier: License :: OSI Approved :: MIT License
Classifier: Natural Language :: English
Classifier: Operating System :: OS Independent
Classifier: Programming Language :: Python :: 3
Classifier: Programming Language :: Python :: 3.10
Classifier: Programming Language :: Python :: 3.11
Classifier: Programming Language :: Python :: 3.12
Classifier: Programming Language :: Python :: 3.13
Classifier: Topic :: Education :: Testing
Classifier: Topic :: Software Development :: Build Tools
Classifier: Topic :: System :: Filesystems
Classifier: Topic :: Text Processing :: Markup :: XML
Classifier: Topic :: Utilities
Classifier: Typing :: Typed
License-File: LICENSE.txt
Requires-Dist: python-fsutil<1.0.0,>=0.9.3
Requires-Dist: python-slugify<9.0.0,>=7.0.0
Requires-Dist: requests<3.0.0,>=2.26.0
Requires-Dist: typing_extensions<4.16.0,>=4.13.2
Requires-Dist: useful-types<0.3.0,>=0.2.1
Provides-Extra: all
Requires-Dist: python-benedict[io,parse,s3]; extra == "all"
Provides-Extra: html
Requires-Dist: beautifulsoup4<5.0.0,>=4.12.0; extra == "html"
Requires-Dist: python-benedict[xml]; extra == "html"
Provides-Extra: io
Requires-Dist: python-benedict[html,toml,xls,xml,yaml]; extra == "io"
Provides-Extra: parse
Requires-Dist: ftfy<7.0.0,>=6.0.0; extra == "parse"
Requires-Dist: mailchecker<7.0.0,>=4.1.0; extra == "parse"
Requires-Dist: phonenumbers<10.0.0,>=8.12.0; extra == "parse"
Requires-Dist: python-dateutil<3.0.0,>=2.8.0; extra == "parse"
Provides-Extra: s3
Requires-Dist: boto3<2.0.0,>=1.24.89; extra == "s3"
Provides-Extra: toml
Requires-Dist: toml<1.0.0,>=0.10.2; extra == "toml"
Provides-Extra: xls
Requires-Dist: openpyxl<4.0.0,>=3.0.0; extra == "xls"
Requires-Dist: xlrd<3.0.0,>=2.0.0; extra == "xls"
Provides-Extra: xml
Requires-Dist: xmltodict<2.0.0,>=0.12.0; extra == "xml"
Provides-Extra: yaml
Requires-Dist: pyyaml<7.0,>=6.0; extra == "yaml"
Dynamic: license-file
